dataon_utils/__init__.py
dataon_utils/azure_token.py
dataon_utils/hierarchy.py
dataon_utils/key_vault.py
dataon_utils/process_file.py
dataon_utils-0.0.4.dist-info/LICENSE.txt
dataon_utils-0.0.4.dist-info/METADATA
dataon_utils-0.0.4.dist-info/WHEEL
dataon_utils-0.0.4.dist-info/top_level.txt
dataon_utils-0.0.4.dist-info/RECORD
