Metadata-Version: 2.1
Name: dataon-utils
Version: 0.0.4
Summary: dataon utils package
Author-email: Mik Laursen <mbl@dataon.dk>, Alexander Tygesen <at@dataon.dk>
Requires-Python: >=3.10
License-File: LICENSE.txt
Requires-Dist: pendulum
Requires-Dist: polars
Requires-Dist: pyspark
Requires-Dist: requests
Provides-Extra: dev
Requires-Dist: pre-commit ; extra == 'dev'
Requires-Dist: ruff ==0.6.5 ; extra == 'dev'
Provides-Extra: test
Requires-Dist: pytest ; extra == 'test'
